CHANGELOG.md
LICENSE
MANIFEST.in
Makefile
README.md
setup.cfg
setup.py
tox.ini
tests/test_parser.py
tests/test_registry.py
tests/test_transformer.py
wc_shortcodes/__init__.py
wc_shortcodes/parser.py
wc_shortcodes/registry.py
wc_shortcodes/transformer.py
wc_shortcodes.egg-info/PKG-INFO
wc_shortcodes.egg-info/SOURCES.txt
wc_shortcodes.egg-info/dependency_links.txt
wc_shortcodes.egg-info/requires.txt
wc_shortcodes.egg-info/top_level.txt
wc_shortcodes/contrib/__init__.py
wc_shortcodes/contrib/django/__init__.py
wc_shortcodes/contrib/django/apps.py